expyrt/__init__.py
expyrt/vapor_pressure.py
expyrt-0.1.1.dist-info/LICENSE
expyrt-0.1.1.dist-info/METADATA
expyrt-0.1.1.dist-info/WHEEL
expyrt-0.1.1.dist-info/top_level.txt
expyrt-0.1.1.dist-info/RECORD
