Metadata-Version: 2.1
Name: expyrt
Version: 0.1.1
Summary: A package for studying data science.
Home-page: UNKNOWN
License: UNKNOWN
Platform: UNKNOWN
License-File: LICENSE
